SBself/__init__.py
SBself/config.py
SBself/core/__init__.py
SBself/core/core_cmds.py
SBself/core/core_commands.py
SBself/core/edit_and_reply.py
SBself/core/final_text.py
SBself/core/gp_id_manager.py
SBself/core/id_manager.py
SBself/core/logger.py
SBself/core/name_manager.py
SBself/core/off_manager.py
SBself/core/show_manager.py
SBself/core/startup_announcer.py
SBself/core/utils.py
SBself/filters/SBfilters.py
SBself/modules/__init__.py
SBself/modules/admin/__init__.py
SBself/modules/admin/admin_commands.py
SBself/modules/admin/admin_manager.py
SBself/modules/backup/__init__.py
SBself/modules/backup/backup_commands.py
SBself/modules/backup/backup_manager.py
SBself/modules/chat/__init__.py
SBself/modules/chat/chat_cleaner.py
SBself/modules/chat/chat_cmds.py
SBself/modules/chat/chat_commands.py
SBself/modules/chat/chat_manager.py
SBself/modules/enemy/__init__.py
SBself/modules/enemy/enemy_commands.py
SBself/modules/enemy/enemy_handlers.py
SBself/modules/enemy/enemy_manager.py
SBself/modules/forward/__init__.py
SBself/modules/forward/forward_cmds.py
SBself/modules/forward/forward_commands.py
SBself/modules/forward/forward_manager.py
SBself/modules/forward/forward_queue_manager.py
SBself/modules/forward/multi_forward_cmds.py
SBself/modules/forward/multi_forward_manager.py
SBself/modules/get_code_login/__init__.py
SBself/modules/get_code_login/getcode_commands.py
SBself/modules/id/__init__.py
SBself/modules/id/id_commands.py
SBself/modules/member/__init__.py
SBself/modules/member/member_handlers.py
SBself/modules/mention/__init__.py
SBself/modules/mention/mention_commands.py
SBself/modules/mention/mention_manager.py
SBself/modules/profile/__init__.py
SBself/modules/profile/profile_commands.py
SBself/modules/profile/profile_manager.py
SBself/modules/relay/relay_commands.py
SBself/modules/spammer/__init__.py
SBself/modules/spammer/auto_timer_handler.py
SBself/modules/spammer/spammer.py
SBself/modules/spammer/spammer_commands.py
SBself/modules/spammer/spammer_manager.py
mtself-1.3.37.dist-info/licenses/LICENSE
mtself-1.3.37.dist-info/METADATA
mtself-1.3.37.dist-info/WHEEL
mtself-1.3.37.dist-info/top_level.txt
mtself-1.3.37.dist-info/RECORD
